__init__.py
main.py
tocrhbnn-1.2.dist-info/LICENSE
tocrhbnn-1.2.dist-info/METADATA
tocrhbnn-1.2.dist-info/WHEEL
tocrhbnn-1.2.dist-info/top_level.txt
tocrhbnn-1.2.dist-info/RECORD
