Metadata-Version: 2.1
Name: tocrhbnn
Version: 1.2
Summary: typesquatting cases
Author-email: Example Author <author@example.com>
Classifier: Programming Language :: Python :: 3
Classifier: License :: OSI Approved :: MIT License
Classifier: Operating System :: OS Independent
Requires-Python: >=3.8
License-File: LICENSE
